{
  "generated_at": "2026-06-09T08:02:00+09:00",
  "fetch_status": {
    "google_trends": "ok",
    "yahoo_news_ranking": "ok",
    "yahoo_realtime": "ok",
    "x_realtime": "ok",
    "news_web": "ok"
  },
  "raw_pool_total": 132,
  "filter": {
    "raw_by_category": {
      "google_trends": 10,
      "news_web": 48,
      "yahoo_news_ranking": 24,
      "yahoo_realtime": 40,
      "x_realtime": 10
    },
    "neg_excluded": 7,
    "dedup_excluded": 10,
    "passed_total": 115,
    "b2b_category_counts": {
      "x_realtime": 7,
      "news_web": 11,
      "google_trends": 10,
      "yahoo_realtime": 37,
      "yahoo_news_ranking": 5
    }
  },
  "note_category_counts": {
    "social_reaction": 25,
    "personal_story": 3,
    "opinion": 10,
    "medical_science": 5,
    "hard_fact": 16,
    "policy": 11
  },
  "b2b_topic_category_counts": {
    "social_reaction": 25,
    "hard_fact": 17,
    "opinion": 10,
    "medical_science": 4,
    "personal_story": 3,
    "policy": 11
  },
  "b2b_top10": [
    {
      "title": "三菱UFJ銀行が『PPAP』を原則廃止するが本質的になにも変わってなくて草生える",
      "source_category": "x_realtime",
      "raw_source_key": "togetter_hot",
      "topic_category": "social_reaction"
    },
    {
      "title": "巨人が夏対策 東京D空調4℃上げ",
      "source_category": "news_web",
      "raw_source_key": "yahoo_news_topics",
      "topic_category": "hard_fact"
    },
    {
      "title": "ブルージェイズ 対 フィリーズ",
      "source_category": "google_trends",
      "raw_source_key": "google_trends",
      "topic_category": "opinion"
    },
    {
      "title": "ワールドカップ 日程",
      "source_category": "google_trends",
      "raw_source_key": "google_trends",
      "topic_category": "opinion"
    },
    {
      "title": "オリオールズ 対 マリナーズ",
      "source_category": "google_trends",
      "raw_source_key": "google_trends",
      "topic_category": "opinion"
    },
    {
      "title": "「ラーメンを食べて駅まで走ったら、突然意識を失って倒れた」これは怪奇現象ではなく",
      "source_category": "yahoo_realtime",
      "raw_source_key": "hatena_hotentry",
      "topic_category": "medical_science"
    },
    {
      "title": "実家近くの空き家を見に行ったら、家はまだ新しいのできれいだし家具もそのまま使って",
      "source_category": "yahoo_realtime",
      "raw_source_key": "hatena_hotentry",
      "topic_category": "personal_story"
    },
    {
      "title": "ヒロイン",
      "source_category": "google_trends",
      "raw_source_key": "google_trends",
      "topic_category": "opinion"
    },
    {
      "title": "バンクオブアメリカ",
      "source_category": "google_trends",
      "raw_source_key": "google_trends",
      "topic_category": "opinion"
    },
    {
      "title": "ワールドカップ 放送",
      "source_category": "google_trends",
      "raw_source_key": "google_trends",
      "topic_category": "opinion"
    }
  ],
  "note_top10": [
    {
      "title": "三菱UFJ銀行が『PPAP』を原則廃止するが本質的になにも変わってなくて草生える",
      "source_category": "x_realtime",
      "raw_source_key": "togetter_hot",
      "topic_category": "social_reaction"
    },
    {
      "title": "実家近くの空き家を見に行ったら、家はまだ新しいのできれいだし家具もそのまま使って",
      "source_category": "yahoo_realtime",
      "raw_source_key": "hatena_hotentry",
      "topic_category": "personal_story"
    },
    {
      "title": "日本の出生率、東アジアで最高に。一部の西洋諸国も上回る（他の国が勝手に、それ以上",
      "source_category": "yahoo_realtime",
      "raw_source_key": "hatena_hotentry",
      "topic_category": "social_reaction"
    },
    {
      "title": "空飛ぶクルマ「ヘリコプターの半額めざす」　スカイドライブ、28年にも商用化 - ",
      "source_category": "yahoo_realtime",
      "raw_source_key": "hatena_hotentry",
      "topic_category": "social_reaction"
    },
    {
      "title": "「一番の償いは私たちの死のみ」旭川の女子高校生殺人事件、内田被告に懲役27年を求",
      "source_category": "x_realtime",
      "raw_source_key": "togetter_hot",
      "topic_category": "personal_story"
    },
    {
      "title": "目標が立てられないのは欠点じゃない！動きながら進むキャリアの作り方 - STUD",
      "source_category": "yahoo_realtime",
      "raw_source_key": "hatena_hotentry",
      "topic_category": "social_reaction"
    },
    {
      "title": "ブルージェイズ 対 フィリーズ",
      "source_category": "google_trends",
      "raw_source_key": "google_trends",
      "topic_category": "opinion"
    },
    {
      "title": "ワールドカップ 日程",
      "source_category": "google_trends",
      "raw_source_key": "google_trends",
      "topic_category": "opinion"
    },
    {
      "title": "オリオールズ 対 マリナーズ",
      "source_category": "google_trends",
      "raw_source_key": "google_trends",
      "topic_category": "opinion"
    },
    {
      "title": "「ラーメンを食べて駅まで走ったら、突然意識を失って倒れた」これは怪奇現象ではなく",
      "source_category": "yahoo_realtime",
      "raw_source_key": "hatena_hotentry",
      "topic_category": "medical_science"
    }
  ]
}